asyncer/__init__.py
asyncer/_compat.py
asyncer/_main.py
asyncer/py.typed
asyncer_slim-0.0.12.dist-info/METADATA
asyncer_slim-0.0.12.dist-info/WHEEL
asyncer_slim-0.0.12.dist-info/entry_points.txt
asyncer_slim-0.0.12.dist-info/licenses/LICENSE
asyncer_slim-0.0.12.dist-info/RECORD
