Metadata-Version: 2.4
Name: asyncer-slim
Version: 0.0.12
Summary: Asyncer, async and await, focused on developer experience.
Author-Email: =?utf-8?q?Sebasti=C3=A1n_Ram=C3=ADrez?= <tiangolo@gmail.com>
License-Expression: MIT
License-File: LICENSE
Classifier: Development Status :: 4 - Beta
Classifier: Framework :: AsyncIO
Classifier: Framework :: Trio
Classifier: Intended Audience :: Developers
Classifier: Intended Audience :: Education
Classifier: Intended Audience :: Information Technology
Classifier: Intended Audience :: Science/Research
Classifier: Intended Audience :: System Administrators
Classifier: Programming Language :: Python :: 3 :: Only
Classifier: Programming Language :: Python :: 3.9
Classifier: Programming Language :: Python :: 3.10
Classifier: Programming Language :: Python :: 3.11
Classifier: Programming Language :: Python :: 3.12
Classifier: Programming Language :: Python :: 3.13
Classifier: Programming Language :: Python :: 3.14
Classifier: Topic :: Internet
Classifier: Typing :: Typed
Project-URL: Homepage, https://github.com/fastapi/asyncer
Project-URL: Documentation, https://asyncer.tiangolo.com
Project-URL: Repository, https://github.com/fastapi/asyncer
Project-URL: Issues, https://github.com/fastapi/asyncer/issues
Project-URL: Changelog, https://asyncer.tiangolo.com/release-notes/
Requires-Python: >=3.9
Requires-Dist: anyio<5.0,>=3.4.0
Requires-Dist: sniffio>=1.1
Requires-Dist: typing_extensions>=4.8.0; python_version < "3.10"
